covidcast/__init__.py
covidcast/covidcast.py
covidcast/errors.py
covidcast/geography.py
covidcast/plotting.py
covidcast/geo_mappings/county_census.csv
covidcast/geo_mappings/msa_census.csv
covidcast/geo_mappings/state_census.csv
covidcast/shapefiles/county/cb_2019_us_county_5m.cpg
covidcast/shapefiles/county/cb_2019_us_county_5m.dbf
covidcast/shapefiles/county/cb_2019_us_county_5m.prj
covidcast/shapefiles/county/cb_2019_us_county_5m.shp
covidcast/shapefiles/county/cb_2019_us_county_5m.shp.ea.iso.xml
covidcast/shapefiles/county/cb_2019_us_county_5m.shp.iso.xml
covidcast/shapefiles/county/cb_2019_us_county_5m.shx
covidcast/shapefiles/hrr/geo_export_ad86cff5-e5ed-432e-9ec2-2ce8732099ee.dbf
covidcast/shapefiles/hrr/geo_export_ad86cff5-e5ed-432e-9ec2-2ce8732099ee.prj
covidcast/shapefiles/hrr/geo_export_ad86cff5-e5ed-432e-9ec2-2ce8732099ee.shp
covidcast/shapefiles/hrr/geo_export_ad86cff5-e5ed-432e-9ec2-2ce8732099ee.shx
covidcast/shapefiles/msa/cb_2019_us_cbsa_5m.cpg
covidcast/shapefiles/msa/cb_2019_us_cbsa_5m.dbf
covidcast/shapefiles/msa/cb_2019_us_cbsa_5m.prj
covidcast/shapefiles/msa/cb_2019_us_cbsa_5m.shp
covidcast/shapefiles/msa/cb_2019_us_cbsa_5m.shp.ea.iso.xml
covidcast/shapefiles/msa/cb_2019_us_cbsa_5m.shp.iso.xml
covidcast/shapefiles/msa/cb_2019_us_cbsa_5m.shx
covidcast/shapefiles/state/cb_2019_us_state_5m.cpg
covidcast/shapefiles/state/cb_2019_us_state_5m.dbf
covidcast/shapefiles/state/cb_2019_us_state_5m.prj
covidcast/shapefiles/state/cb_2019_us_state_5m.shp
covidcast/shapefiles/state/cb_2019_us_state_5m.shp.ea.iso.xml
covidcast/shapefiles/state/cb_2019_us_state_5m.shp.iso.xml
covidcast/shapefiles/state/cb_2019_us_state_5m.shx
covidcast-0.2.2.dist-info/LICENSE
covidcast-0.2.2.dist-info/METADATA
covidcast-0.2.2.dist-info/WHEEL
covidcast-0.2.2.dist-info/top_level.txt
covidcast-0.2.2.dist-info/RECORD
