Metadata-Version: 2.1
Name: covidcast
Version: 0.2.2
Summary: Access COVID-19 data through the Delphi COVIDcast API
Home-page: https://cmu-delphi.github.io/covidcast/covidcast-py/html/
Author: Alex Reinhart
Author-email: areinhar@stat.cmu.edu
License: UNKNOWN
Platform: UNKNOWN
Classifier: Programming Language :: Python :: 3
Classifier: License :: OSI Approved :: MIT License
Classifier: Operating System :: OS Independent
Requires-Python: >=3.6
Requires-Dist: pandas (<2)
Requires-Dist: requests
Requires-Dist: delphi-epidata (==4.*,>=4.1.11)
Requires-Dist: geopandas
Requires-Dist: matplotlib
Requires-Dist: numpy
Requires-Dist: descartes
Requires-Dist: imageio-ffmpeg
Requires-Dist: imageio
Requires-Dist: tqdm
Requires-Dist: epiweeks
